sdh.table3-2.1.0-py3.11-nspkg.pth
sdh/table3/__init__.py
sdh/table3/bound.py
sdh/table3/column.py
sdh/table3/data.py
sdh/table3/plugin.py
sdh/table3/render.py
sdh/table3/request.py
sdh/table3/settings.py
sdh/table3/table.py
sdh/table3/plugins/__init__.py
sdh/table3/plugins/actions.py
sdh/table3/plugins/button.py
sdh/table3/plugins/filters.py
sdh/table3/plugins/header.py
sdh/table3/plugins/output.py
sdh/table3/plugins/paginator.py
sdh/table3/plugins/quicksearch.py
sdh/table3/plugins/sortable.py
sdh/table3/templates/sdh/table3/category.html
sdh/table3/templates/sdh/table3/dropdown.html
sdh/table3/templates/sdh/table3/header_checkbox.html
sdh/table3/templates/sdh/table3/header_column.html
sdh/table3/templates/sdh/table3/main.html
sdh/table3/templates/sdh/table3/paginator.html
sdh/table3/templates/sdh/table3/post_action.html
sdh/table3/templates/sdh/table3/quicksearch.html
sdh/table3/templatetags/__init__.py
sdh/table3/templatetags/table3.py
sdh.table3-2.1.0.dist-info/LICENSE
sdh.table3-2.1.0.dist-info/METADATA
sdh.table3-2.1.0.dist-info/WHEEL
sdh.table3-2.1.0.dist-info/eager_resources.txt
sdh.table3-2.1.0.dist-info/namespace_packages.txt
sdh.table3-2.1.0.dist-info/top_level.txt
sdh.table3-2.1.0.dist-info/RECORD
