Metadata-Version: 2.1
Name: sdh.table3
Version: 2.1.0
Summary: Table rendering engine
Home-page: https://github.com/sdh-global/sdh-table3
Author: Oleg Koziy
Author-email: Viacheslav Vic Bukhantsov <vic.bukhantsov@gmail.com>, Andiy Koziy <andriy@koziy.com>, Alexey Babarykin <mobil.light@gmail.com>, "Alex V. Koval" <alex@ua2web.com>, Alexander Tsiskovsky aka Lextor <lextor.alex@gmail.com>
Maintainer-email: Viacheslav Vic Bukhantsov <vic.bukhantsov@gmail.com>
License: Copyright (c) 2024, SDH-IT GmbH
Project-URL: Repository, https://github.com/sdh-global/sdh-table3
Classifier: Development Status :: 5 - Production/Stable
Classifier: Environment :: Web Environment
Classifier: Framework :: Django
Classifier: Intended Audience :: Developers
Classifier: License :: OSI Approved :: BSD License
Classifier: Operating System :: OS Independent
Classifier: Programming Language :: Python
Classifier: Programming Language :: Python :: 3
Classifier: Programming Language :: Python :: 3.8
Classifier: Programming Language :: Python :: 3.9
Classifier: Topic :: Internet :: WWW/HTTP
Classifier: Topic :: Internet :: WWW/HTTP :: Dynamic Content
Classifier: Topic :: Software Development :: Libraries :: Python Modules
Requires-Python: >=3.8
License-File: LICENSE
Requires-Dist: Django >=3.2
